setup.py
eos_python_utils/__init__.py
eos_python_utils.egg-info/PKG-INFO
eos_python_utils.egg-info/SOURCES.txt
eos_python_utils.egg-info/dependency_links.txt
eos_python_utils.egg-info/not-zip-safe
eos_python_utils.egg-info/top_level.txt