Metadata-Version: 1.0
Name: eos-python-utils
Version: 0.0.3
Summary: python route handling for eos-redux
Home-page: https://github.com/travisoneill/python-utils-eos-redux
Author: Travis Oneill
Author-email: travis.h.oneill@gmail.com
License: UNKNOWN
Platform: UNKNOWN
